pdf_chunk_flow/__init__.py
pdf_chunk_flow/main.py
pdf_chunk_flow/contracts/__init__.py
pdf_chunk_flow/contracts/contracts.py
pdf_chunk_flow/extract/__init__.py
pdf_chunk_flow/extract/extract.py
pdf_chunk_flow/load/__init__.py
pdf_chunk_flow/load/load.py
pdf_chunk_flow/tranform/__init__.py
pdf_chunk_flow/tranform/transform.py
pdf_chunk_flow-0.1.1.dist-info/licenses/LICENSE
pdf_chunk_flow-0.1.1.dist-info/METADATA
pdf_chunk_flow-0.1.1.dist-info/WHEEL
pdf_chunk_flow-0.1.1.dist-info/entry_points.txt
pdf_chunk_flow-0.1.1.dist-info/top_level.txt
pdf_chunk_flow-0.1.1.dist-info/RECORD
