Metadata-Version: 2.4
Name: pdf-chunk-flow
Version: 0.1.1
Summary: ETL pipeline for PDF processing with chunking and parquet storage optimized for embeddings
Home-page: https://github.com/facuvegaingenieer/pdf_chunk_flow
Author: Walter Facundo Vega
Author-email: Facundo Vega <facundo.vega1234@gmail.com>
License: MIT
Project-URL: Homepage, https://github.com/facuvegaingenieer/pdf_chunk_flow
Project-URL: Documentation, https://github.com/facuvegaingenieer/pdf_chunk_flow#readme
Project-URL: Repository, https://github.com/facuvegaingenieer/pdf_chunk_flow
Project-URL: Bug Tracker, https://github.com/facuvegaingenieer/pdf_chunk_flow/issues
Keywords: pdf,etl,pipeline,embeddings,parquet,nlp,chunks,rag
Classifier: Development Status :: 4 - Beta
Classifier: Intended Audience :: Developers
Classifier: License :: OSI Approved :: MIT License
Classifier: Programming Language :: Python :: 3
Classifier: Programming Language :: Python :: 3.9
Classifier: Programming Language :: Python :: 3.10
Classifier: Programming Language :: Python :: 3.11
Classifier: Programming Language :: Python :: 3.12
Classifier: Topic :: Software Development :: Libraries :: Python Modules
Classifier: Topic :: Scientific/Engineering :: Artificial Intelligence
Classifier: Topic :: Text Processing
Requires-Python: >=3.8
License-File: LICENSE
Requires-Dist: requests>=2.31.0
Requires-Dist: pypdf>=3.17.0
Requires-Dist: pandas>=2.1.0
Requires-Dist: pyarrow>=14.0.0
Requires-Dist: python-dotenv>=1.0.0
Provides-Extra: dev
Requires-Dist: pytest>=7.4.0; extra == "dev"
Requires-Dist: pytest-cov>=4.1.0; extra == "dev"
Requires-Dist: pytest-mock>=3.11.0; extra == "dev"
Dynamic: author
Dynamic: home-page
Dynamic: license-file
Dynamic: requires-python
